oscars/__init__.py
oscars/bl.py
oscars/brightness.py
oscars/fit.py
oscars/lut.py
oscars/me.py
oscars/parametric_surfaces.py
oscars/plots3d_mpl.py
oscars/plots_mpl.py
oscars/sr.cpython-37m-darwin.so
oscars/th.cpython-37m-darwin.so
oscars/twiss.py
oscars/util.py
oscars-2.1.8.data/data/oscars/COPYRIGHT.txt
oscars-2.1.8.data/data/oscars/LICENSE.txt
oscars-2.1.8.dist-info/METADATA
oscars-2.1.8.dist-info/RECORD
oscars-2.1.8.dist-info/WHEEL
oscars-2.1.8.dist-info/top_level.txt
