Metadata-Version: 2.1
Name: oscars
Version: 2.1.8
Summary: Open Source Code for Advanced Radiation Simulation
Home-page: http://oscars.bnl.gov/
Author: Dean Andrew Hidas
Author-email: dhidas@bnl.gov
License: LICENSE.txt
Platform: UNKNOWN
